tempconvert/__init__.py
tempconvert_atharv22-0.1.3.dist-info/METADATA
tempconvert_atharv22-0.1.3.dist-info/WHEEL
tempconvert_atharv22-0.1.3.dist-info/RECORD
