Metadata-Version: 2.3
Name: tempconvert-atharv22
Version: 0.1.3
Summary: A simple temperature conversion tool
License: MIT
Author: Atharv
Author-email: atharvachaugale22@gmail.com
Requires-Python: >=3.9
Classifier: License :: OSI Approved :: MIT License
Classifier: Programming Language :: Python :: 3
Classifier: Programming Language :: Python :: 3.9
Classifier: Programming Language :: Python :: 3.10
Classifier: Programming Language :: Python :: 3.11
Classifier: Programming Language :: Python :: 3.12
Classifier: Programming Language :: Python :: 3.13
